README.rst
setup.cfg
setup.py
liccheck/__init__.py
liccheck/__main__.py
liccheck/command_line.py
liccheck/requirements.py
liccheck_regex.egg-info/PKG-INFO
liccheck_regex.egg-info/SOURCES.txt
liccheck_regex.egg-info/dependency_links.txt
liccheck_regex.egg-info/entry_points.txt
liccheck_regex.egg-info/requires.txt
liccheck_regex.egg-info/top_level.txt