Metadata-Version: 1.2
Name: liccheck-regex
Version: 0.7.4
Summary: Check python packages from requirement.txt and report issues
Home-page: https://github.com/dhatim/python-license-check
Author: Dhatim
Author-email: contact@dhatim.com
License: Apache Software License
Keywords: license check build tool
Platform: UNKNOWN
Classifier: Development Status :: 5 - Production/Stable
Classifier: Intended Audience :: Developers
Classifier: Topic :: Software Development :: Build Tools
Classifier: License :: OSI Approved :: Apache Software License
Classifier: Programming Language :: Python :: 2
Classifier: Programming Language :: Python :: 2.7
Classifier: Programming Language :: Python :: 3
Classifier: Programming Language :: Python :: 3.5
Classifier: Programming Language :: Python :: 3.6
Classifier: Programming Language :: Python :: 3.7
Classifier: Programming Language :: Python :: 3.8
Requires-Python: >=2.7
